<?xml version="1.0" encoding="UTF-8"?><record_update sys_domain="global" table="sys_hub_flow">
    <sys_hub_flow action="DELETE">
        <access>public</access>
        <acls/>
        <active>false</active>
        <annotation/>
        <attributes/>
        <authored_on_release_version>27000</authored_on_release_version>
        <callable_by_client_api>false</callable_by_client_api>
        <category/>
        <compiler_build/>
        <copied_from>9a41b6c2ff12101088e94ee9453bf1a4</copied_from>
        <copied_from_name>FlowTemplate_Empty</copied_from_name>
        <description/>
        <display_name_after_preview/>
        <flow_priority/>
        <generation_source/>
        <internal_name>onboarding_applications</internal_name>
        <label_cache>[]</label_cache>
        <latest_snapshot/>
        <master_snapshot/>
        <master_snapshot_digest/>
        <name>Onboarding Applications</name>
        <natlang/>
        <outputs/>
        <pre_compiled>false</pre_compiled>
        <remote_trigger_id/>
        <run_as>system</run_as>
        <run_with_roles/>
        <sc_callable>false</sc_callable>
        <show_draft_actions>false</show_draft_actions>
        <show_triggered_flows>false</show_triggered_flows>
        <status>draft</status>
        <substatus/>
        <sys_class_name>sys_hub_flow</sys_class_name>
        <sys_created_by>admin</sys_created_by>
        <sys_created_on>2025-05-26 08:00:25</sys_created_on>
        <sys_domain>global</sys_domain>
        <sys_domain_path>/</sys_domain_path>
        <sys_id>e4fe60749775a6102e5cfefce053af9c</sys_id>
        <sys_mod_count>0</sys_mod_count>
        <sys_name>Onboarding Applications</sys_name>
        <sys_overrides/>
        <sys_package display_value="Demo1" source="x_1758226_demo1">4112a0349735a6102e5cfefce053afde</sys_package>
        <sys_policy/>
        <sys_scope display_value="Demo1">4112a0349735a6102e5cfefce053afde</sys_scope>
        <sys_update_name>sys_hub_flow_e4fe60749775a6102e5cfefce053af9c</sys_update_name>
        <sys_updated_by>admin</sys_updated_by>
        <sys_updated_on>2025-05-26 08:00:25</sys_updated_on>
        <type>flow</type>
        <updation_source/>
        <version>2</version>
    </sys_hub_flow>
    <sys_translated_text action="DELETE" query="documentkey=e4fe60749775a6102e5cfefce053af9c"/>
    <sys_variable_value action="DELETE" query="document_key=e4fe60749775a6102e5cfefce053af9c"/>
    <sys_hub_flow_stage action="DELETE" query="flow=e4fe60749775a6102e5cfefce053af9c"/>
    <sys_flow_cat_variable_model action="DELETE" query="id=e4fe60749775a6102e5cfefce053af9c^sys_idNOT IN64fe60749775a6102e5cfefce053af9d"/>
    <sys_flow_cat_variable_model action="DELETE">
        <id>e4fe60749775a6102e5cfefce053af9c</id>
        <name>Onboarding Applications</name>
        <sys_created_by>admin</sys_created_by>
        <sys_created_on>2025-05-26 08:00:25</sys_created_on>
        <sys_id>64fe60749775a6102e5cfefce053af9d</sys_id>
        <sys_mod_count>0</sys_mod_count>
        <sys_scope/>
        <sys_updated_by>admin</sys_updated_by>
        <sys_updated_on>2025-05-26 08:00:25</sys_updated_on>
    </sys_flow_cat_variable_model>
    <sys_flow_cat_variable action="DELETE" query="flow_catalog_model=64fe60749775a6102e5cfefce053af9d"/>
    <sys_hub_flow_input action="DELETE" query="model=e4fe60749775a6102e5cfefce053af9c"/>
    <sys_hub_flow_output action="DELETE" query="model=e4fe60749775a6102e5cfefce053af9c"/>
    <sys_hub_alias_mapping action="DELETE" query="source_id=e4fe60749775a6102e5cfefce053af9c"/>
    <sys_hub_trigger_instance_v2 action="DELETE" query="flow=e4fe60749775a6102e5cfefce053af9c"/>
    <sys_hub_action_instance_v2 action="DELETE" query="flow=e4fe60749775a6102e5cfefce053af9c"/>
    <sys_hub_sub_flow_instance_v2 action="DELETE" query="flow=e4fe60749775a6102e5cfefce053af9c"/>
    <sys_hub_flow_logic_instance_v2 action="DELETE" query="flow=e4fe60749775a6102e5cfefce053af9c"/>
    <sys_hub_pill_compound action="DELETE" query="attached_to=e4fe60749775a6102e5cfefce053af9c"/>
    <sys_hub_flow_variable action="DELETE" query="model=e4fe60749775a6102e5cfefce053af9c"/>
    <sys_choice action="DELETE" query="name=var__m_sys_hub_flow_input_e4fe60749775a6102e5cfefce053af9c"/>
    <sys_choice action="DELETE" query="name=var__m_sys_hub_flow_output_e4fe60749775a6102e5cfefce053af9c"/>
    <sys_flow_trigger_plan action="DELETE" query="plan_id=e4fe60749775a6102e5cfefce053af9c"/>
    <sys_flow_subflow_plan action="DELETE" query="plan_id=e4fe60749775a6102e5cfefce053af9c"/>
    <sys_update_version action="INSERT_OR_UPDATE">
        <action>DELETE</action>
        <application display_value="Demo1">4112a0349735a6102e5cfefce053afde</application>
        <file_path/>
        <instance_id>e73c1526eb556e503a48f459bad0cdfe</instance_id>
        <instance_name>dev346983</instance_name>
        <name>sys_hub_flow_e4fe60749775a6102e5cfefce053af9c</name>
        <payload><![CDATA[<?xml version="1.0" encoding="UTF-8"?><record_update sys_domain="global" table="sys_hub_flow"><sys_hub_flow action="INSERT_OR_UPDATE"><access>public</access><acls/><active>false</active><annotation/><attributes/><authored_on_release_version>27000</authored_on_release_version><callable_by_client_api>false</callable_by_client_api><category/><compiler_build/><copied_from>9a41b6c2ff12101088e94ee9453bf1a4</copied_from><copied_from_name>FlowTemplate_Empty</copied_from_name><description/><display_name_after_preview/><flow_priority/><generation_source/><internal_name>onboarding_applications</internal_name><label_cache>[]</label_cache><latest_snapshot/><master_snapshot/><master_snapshot_digest/><name>Onboarding Applications</name><natlang/><outputs/><pre_compiled>false</pre_compiled><remote_trigger_id/><run_as>system</run_as><run_with_roles/><sc_callable>false</sc_callable><show_draft_actions>false</show_draft_actions><show_triggered_flows>false</show_triggered_flows><status>draft</status><substatus/><sys_class_name>sys_hub_flow</sys_class_name><sys_created_by>admin</sys_created_by><sys_created_on>2025-05-26 08:00:25</sys_created_on><sys_domain>global</sys_domain><sys_domain_path>/</sys_domain_path><sys_id>e4fe60749775a6102e5cfefce053af9c</sys_id><sys_mod_count>0</sys_mod_count><sys_name>Onboarding Applications</sys_name><sys_overrides/><sys_package display_value="Demo1" source="x_1758226_demo1">4112a0349735a6102e5cfefce053afde</sys_package><sys_policy/><sys_scope display_value="Demo1">4112a0349735a6102e5cfefce053afde</sys_scope><sys_update_name>sys_hub_flow_e4fe60749775a6102e5cfefce053af9c</sys_update_name><sys_updated_by>admin</sys_updated_by><sys_updated_on>2025-05-26 08:00:25</sys_updated_on><type>flow</type><updation_source/><version>2</version></sys_hub_flow><sys_translated_text action="delete_multiple" query="documentkey=e4fe60749775a6102e5cfefce053af9c"/><sys_variable_value action="delete_multiple" query="document_key=e4fe60749775a6102e5cfefce053af9c"/><sys_hub_flow_stage action="delete_multiple" query="flow=e4fe60749775a6102e5cfefce053af9c"/><sys_flow_cat_variable_model action="delete_multiple" query="id=e4fe60749775a6102e5cfefce053af9c^sys_idNOT IN64fe60749775a6102e5cfefce053af9d"/><sys_flow_cat_variable_model action="INSERT_OR_UPDATE"><id>e4fe60749775a6102e5cfefce053af9c</id><name>Onboarding Applications</name><sys_created_by>admin</sys_created_by><sys_created_on>2025-05-26 08:00:25</sys_created_on><sys_id>64fe60749775a6102e5cfefce053af9d</sys_id><sys_mod_count>0</sys_mod_count><sys_scope/><sys_updated_by>admin</sys_updated_by><sys_updated_on>2025-05-26 08:00:25</sys_updated_on></sys_flow_cat_variable_model><sys_flow_cat_variable action="delete_multiple" query="flow_catalog_model=64fe60749775a6102e5cfefce053af9d"/><sys_hub_flow_input action="delete_multiple" query="model=e4fe60749775a6102e5cfefce053af9c"/><sys_hub_flow_output action="delete_multiple" query="model=e4fe60749775a6102e5cfefce053af9c"/><sys_hub_alias_mapping action="delete_multiple" query="source_id=e4fe60749775a6102e5cfefce053af9c"/><sys_hub_trigger_instance_v2 action="delete_multiple" query="flow=e4fe60749775a6102e5cfefce053af9c"/><sys_hub_action_instance_v2 action="delete_multiple" query="flow=e4fe60749775a6102e5cfefce053af9c"/><sys_hub_sub_flow_instance_v2 action="delete_multiple" query="flow=e4fe60749775a6102e5cfefce053af9c"/><sys_hub_flow_logic_instance_v2 action="delete_multiple" query="flow=e4fe60749775a6102e5cfefce053af9c"/><sys_hub_pill_compound action="delete_multiple" query="attached_to=e4fe60749775a6102e5cfefce053af9c"/><sys_hub_flow_variable action="delete_multiple" query="model=e4fe60749775a6102e5cfefce053af9c"/><sys_choice action="delete_multiple" query="name=var__m_sys_hub_flow_input_e4fe60749775a6102e5cfefce053af9c"/><sys_choice action="delete_multiple" query="name=var__m_sys_hub_flow_output_e4fe60749775a6102e5cfefce053af9c"/><sys_flow_trigger_plan action="delete_multiple" query="plan_id=e4fe60749775a6102e5cfefce053af9c"/><sys_flow_subflow_plan action="delete_multiple" query="plan_id=e4fe60749775a6102e5cfefce053af9c"/></record_update>]]></payload>
        <payload_hash>423457486</payload_hash>
        <record_name>Onboarding Applications</record_name>
        <reverted_from/>
        <source>5112a0349735a6102e5cfefce053aff9</source>
        <source_table>sys_update_set</source_table>
        <state>previous</state>
        <sys_created_by>admin</sys_created_by>
        <sys_created_on>2025-05-26 08:00:25</sys_created_on>
        <sys_id>f4fe60749775a6102e5cfefce053afa1</sys_id>
        <sys_mod_count>0</sys_mod_count>
        <sys_recorded_at>1970b9b70dc0000001</sys_recorded_at>
        <sys_updated_by>admin</sys_updated_by>
        <sys_updated_on>2025-05-26 08:00:25</sys_updated_on>
        <type>Flow</type>
        <update_guid>f8fe6074e075a610403b46bd425b77a0</update_guid>
        <update_guid_history>f8fe6074e075a610403b46bd425b77a0:423457486</update_guid_history>
    </sys_update_version>
    <sys_metadata_delete action="INSERT_OR_UPDATE">
        <sys_audit_delete/>
        <sys_class_name>sys_metadata_delete</sys_class_name>
        <sys_created_by>admin</sys_created_by>
        <sys_created_on>2025-05-26 08:01:24</sys_created_on>
        <sys_db_object display_value="" name="sys_hub_flow">sys_hub_flow</sys_db_object>
        <sys_id>4664f03f442549ea824a8a24342f67f9</sys_id>
        <sys_metadata>e4fe60749775a6102e5cfefce053af9c</sys_metadata>
        <sys_mod_count>0</sys_mod_count>
        <sys_name>Onboarding Applications</sys_name>
        <sys_package display_value="Demo1" source="x_1758226_demo1">4112a0349735a6102e5cfefce053afde</sys_package>
        <sys_parent/>
        <sys_policy/>
        <sys_scope display_value="Demo1">4112a0349735a6102e5cfefce053afde</sys_scope>
        <sys_scope_delete display_value="">8f10db75a89541d698875662ba2aade4</sys_scope_delete>
        <sys_update_name>sys_hub_flow_e4fe60749775a6102e5cfefce053af9c</sys_update_name>
        <sys_update_version display_value="sys_hub_flow_e4fe60749775a6102e5cfefce053af9c">f4fe60749775a6102e5cfefce053afa1</sys_update_version>
        <sys_updated_by>admin</sys_updated_by>
        <sys_updated_on>2025-05-26 08:01:24</sys_updated_on>
    </sys_metadata_delete>
</record_update>
